docs/example_ui.png
docs/index.md
docs/Concepts/mental-model-and-philosophy.md
docs/Contributing/index.md
docs/Contributing/roadmap.md
docs/Decisions/ADR-001-Chat-vs-Completion-Endpoint-Features.md
docs/Gallery/dataflow_pipelines.md
docs/Gallery/dataflow_pipelines.mermaid
docs/Gallery/research_assistant.md
docs/Gallery/research_assistant.mermaid
docs/Gallery/simple_chatbot.md
docs/Gallery/simple_chatbot.mermaid
docs/How To/Authentication/configure_aws_authentication.md
docs/How To/Authentication/use_api_key_authentication.md
docs/How To/Command Line Usage/load_multiple_inputs_from_files.md
docs/How To/Command Line Usage/pass_inputs_on_the_cli.md
docs/How To/Command Line Usage/serve_with_auto_reload.md
docs/How To/Data Processing/adjust_concurrency.md
docs/How To/Data Processing/cache_step_results.md
docs/How To/Data Processing/decode_json_xml.md
docs/How To/Data Processing/explode_collections.md
docs/How To/Data Processing/gather_results.md
docs/How To/Data Processing/read_data_from_files.md
docs/How To/Data Processing/read_sql_databases.md
docs/How To/Data Processing/write_data_to_file.md
docs/How To/Invoke Models/call_large_language_models.md
docs/How To/Invoke Models/create_embeddings.md
docs/How To/Invoke Models/reuse_prompts_with_templates.md
docs/How To/Language Features/include_qtype_yaml.md
docs/How To/Language Features/include_raw_text_from_other_files.md
docs/How To/Language Features/reference_entities_by_id.md
docs/How To/Language Features/use_environment_variables.md
docs/How To/Language Features/use_qtype_mcp.md
docs/How To/Observability & Debugging/trace_calls_with_open_telemetry.md
docs/How To/Observability & Debugging/validate_qtype_yaml.md
docs/How To/Observability & Debugging/visualize_application_architecture.md
docs/How To/Observability & Debugging/visualize_example.mermaid
docs/How To/Qtype Server/flow_as_ui.png
docs/How To/Qtype Server/serve_flows_as_apis.md
docs/How To/Qtype Server/serve_flows_as_ui.md
qtype-0.1.12.dist-info/licenses/LICENSE
qtype-0.1.12.dist-info/METADATA
qtype-0.1.12.dist-info/WHEEL
qtype-0.1.12.dist-info/entry_points.txt
qtype-0.1.12.dist-info/top_level.txt
qtype-0.1.12.dist-info/RECORD
